pyramid_ssm_settings.py
pyramid_ssm_settings-0.2.0.dist-info/LICENSE
pyramid_ssm_settings-0.2.0.dist-info/WHEEL
pyramid_ssm_settings-0.2.0.dist-info/METADATA
pyramid_ssm_settings-0.2.0.dist-info/RECORD
